testfaipackage/__init__.py
testfaipackage/functions.py
test_fai_package-0.1.1.dist-info/LICENSE
test_fai_package-0.1.1.dist-info/METADATA
test_fai_package-0.1.1.dist-info/WHEEL
test_fai_package-0.1.1.dist-info/top_level.txt
test_fai_package-0.1.1.dist-info/RECORD
