Metadata-Version: 2.1
Name: test-fai-package
Version: 0.1.1
Summary: This is a test package for fai
Requires-Python: >=3.10
License-File: LICENSE
Requires-Dist: uv==0.5.4
